pinax/__init__.py
pinax/ratings/__init__.py
pinax/ratings/apps.py
pinax/ratings/categories.py
pinax/ratings/managers.py
pinax/ratings/models.py
pinax/ratings/urls.py
pinax/ratings/views.py
pinax/ratings/migrations/0001_initial.py
pinax/ratings/migrations/0002_auto_20170819_1121.py
pinax/ratings/migrations/0003_auto_20170819_1127.py
pinax/ratings/migrations/__init__.py
pinax/ratings/static/pinax/ratings/img/background.gif
pinax/ratings/static/pinax/ratings/img/cancel-off-big.png
pinax/ratings/static/pinax/ratings/img/cancel-off.png
pinax/ratings/static/pinax/ratings/img/cancel-on-big.png
pinax/ratings/static/pinax/ratings/img/cancel-on.png
pinax/ratings/static/pinax/ratings/img/coffee.png
pinax/ratings/static/pinax/ratings/img/face-a.png
pinax/ratings/static/pinax/ratings/img/face-b.png
pinax/ratings/static/pinax/ratings/img/face-c.png
pinax/ratings/static/pinax/ratings/img/face-d.png
pinax/ratings/static/pinax/ratings/img/face-off.png
pinax/ratings/static/pinax/ratings/img/medal-off.png
pinax/ratings/static/pinax/ratings/img/medal-on.png
pinax/ratings/static/pinax/ratings/img/star-half-big.png
pinax/ratings/static/pinax/ratings/img/star-half.png
pinax/ratings/static/pinax/ratings/img/star-off-big.png
pinax/ratings/static/pinax/ratings/img/star-off.png
pinax/ratings/static/pinax/ratings/img/star-on-big.png
pinax/ratings/static/pinax/ratings/img/star-on.png
pinax/ratings/static/pinax/ratings/js/jquery.raty.js
pinax/ratings/templates/pinax/ratings/_rating.html
pinax/ratings/templates/pinax/ratings/_script.html
pinax/ratings/templatetags/__init__.py
pinax/ratings/templatetags/pinax_ratings_tags.py
pinax/ratings/tests/__init__.py
pinax/ratings/tests/models.py
pinax/ratings/tests/test.py
pinax/ratings/tests/test_models.py
pinax/ratings/tests/test_tags.py
pinax/ratings/tests/test_views.py
pinax/ratings/tests/urls.py
pinax_ratings-4.0.0.dist-info/AUTHORS
pinax_ratings-4.0.0.dist-info/LICENSE
pinax_ratings-4.0.0.dist-info/METADATA
pinax_ratings-4.0.0.dist-info/WHEEL
pinax_ratings-4.0.0.dist-info/top_level.txt
pinax_ratings-4.0.0.dist-info/RECORD
